zea/__init__.py
zea/__main__.py
zea/agent/__init__.py
zea/agent/gumbel.py
zea/agent/masks.py
zea/agent/selection.py
zea/backend/__init__.py
zea/backend/autograd.py
zea/backend/jax/__init__.py
zea/backend/tensorflow/__init__.py
zea/backend/tensorflow/dataloader.py
zea/backend/tensorflow/layers/__init__.py
zea/backend/tensorflow/layers/apodization.py
zea/backend/tensorflow/layers/utils.py
zea/backend/tensorflow/losses.py
zea/backend/tensorflow/models/__init__.py
zea/backend/tensorflow/models/lista.py
zea/backend/tensorflow/scripts/convert-echonet-dynamic.py
zea/backend/tensorflow/scripts/convert-taesd.py
zea/backend/tensorflow/utils/__init__.py
zea/backend/tensorflow/utils/callbacks.py
zea/backend/tensorflow/utils/utils.py
zea/backend/tf2jax.py
zea/backend/torch/__init__.py
zea/backend/torch/losses.py
zea/beamform/__init__.py
zea/beamform/beamformer.py
zea/beamform/delays.py
zea/beamform/lens_correction.py
zea/beamform/pfield.py
zea/beamform/phantoms.py
zea/beamform/pixelgrid.py
zea/config.py
zea/data/__init__.py
zea/data/__main__.py
zea/data/augmentations.py
zea/data/convert/__init__.py
zea/data/convert/__main__.py
zea/data/convert/camus.py
zea/data/convert/echonet.py
zea/data/convert/echonetlvh/README.md
zea/data/convert/echonetlvh/__init__.py
zea/data/convert/echonetlvh/manual_rejections.txt
zea/data/convert/echonetlvh/precompute_crop.py
zea/data/convert/images.py
zea/data/convert/picmus.py
zea/data/convert/utils.py
zea/data/convert/verasonics.py
zea/data/data_format.py
zea/data/dataloader.py
zea/data/datasets.py
zea/data/file.py
zea/data/file_operations.py
zea/data/layers.py
zea/data/preset_utils.py
zea/data/utils.py
zea/datapaths.py
zea/display.py
zea/doppler.py
zea/func/__init__.py
zea/func/tensor.py
zea/func/ultrasound.py
zea/interface.py
zea/internal/_generate_keras_ops.py
zea/internal/cache.py
zea/internal/checks.py
zea/internal/config/create.py
zea/internal/config/parameters.py
zea/internal/config/validation.py
zea/internal/core.py
zea/internal/device.py
zea-0.0.9.dist-info/METADATA
zea-0.0.9.dist-info/WHEEL
zea-0.0.9.dist-info/entry_points.txt
zea-0.0.9.dist-info/licenses/LICENSE
zea-0.0.9.dist-info/RECORD
